<?xml version="1.0" encoding="UTF-8" standalone="yes"?>
<imgdir name="1541018.img">
<imgdir name="info">
<int name="hideName" value="1"/>
<imgdir name="script">
<imgdir name="0">
<string name="script" value="seal_Change"/>
</imgdir>
</imgdir>
<int name="dcLeft" value="-50"/>
<int name="dcTop" value="-230"/>
<int name="dcRight" value="50"/>
<int name="dcBottom" value="0"/>
</imgdir>
<imgdir name="stand">
<canvas name="0" width="93" height="241">
<vector name="origin" x="47" y="231"/>
<int name="z" value="0"/>
<int name="delay" value="150"/>
<string name="_hash" value="9b836067d22400e0cd6bb94ce2b592caddc3d206a5ae0aecdc78648114b31741"/>
</canvas>
<canvas name="1" width="93" height="241">
<vector name="origin" x="47" y="231"/>
<int name="z" value="0"/>
<int name="delay" value="150"/>
<string name="_hash" value="2845143c97623c8bb69bfa2e2ccf389c026a3e1c5909822a41baf4a66cc74044"/>
</canvas>
<canvas name="2" width="93" height="241">
<vector name="origin" x="47" y="231"/>
<int name="z" value="0"/>
<int name="delay" value="150"/>
<string name="_hash" value="bd81351bf76b9e3a7675e85dd1ba39015a7f59299a5bafba647edda6c4c3cc2d"/>
</canvas>
<canvas name="3" width="93" height="241">
<vector name="origin" x="47" y="231"/>
<int name="z" value="0"/>
<int name="delay" value="150"/>
<string name="_hash" value="32ab6b77f9ae868bc05667c5eb7f7562cbee40f2680735a8fe4d3279c5726d89"/>
</canvas>
<canvas name="4" width="93" height="241">
<vector name="origin" x="47" y="231"/>
<int name="z" value="0"/>
<int name="delay" value="150"/>
<string name="_hash" value="2ce91cdd8565625cc6d51510290d98668be7e7564fdf0c31f68955703b68f70e"/>
</canvas>
<canvas name="5" width="93" height="241">
<vector name="origin" x="47" y="231"/>
<int name="z" value="0"/>
<int name="delay" value="150"/>
<string name="_hash" value="f5cd4baec914809c10f1706cc00384cd347899d597296e8f8b8288b9ca07a8e5"/>
</canvas>
</imgdir>
</imgdir>
