<?xml version="1.0" encoding="UTF-8" standalone="yes"?><imgdir name="9401240.img"><imgdir name="info"><imgdir name="script"><imgdir name="0"><string name="script" value="npc_9401240"/></imgdir></imgdir></imgdir><imgdir name="stand"><canvas name="0" width="140" height="175"><vector name="origin" x="63" y="170"/><int name="z" value="0"/><string name="_hash" value="5aa866eb45ddb0822586732a97fe7d60b66cb232c000525d42045aefcf6d6e00"/></canvas><canvas name="1" width="141" height="174"><vector name="origin" x="63" y="169"/><int name="z" value="0"/><string name="_hash" value="dcdd0470ed7412be9119423e7c594e807074e05f5d5ddef13593a20edf26b5c9"/></canvas><canvas name="2" width="141" height="172"><vector name="origin" x="63" y="168"/><int name="z" value="0"/><string name="_hash" value="b9926f6f88baa60ebfdf4f166f4b0a906503e3bacc1919cbc2326c134874f794"/></canvas><canvas name="3" width="141" height="172"><vector name="origin" x="63" y="167"/><int name="z" value="0"/><string name="_hash" value="4da0d7dd1dc71e5b77d3287750e1565e11740b37760d8e000cf5f0cfed4f773a"/></canvas><canvas name="4" width="140" height="173"><vector name="origin" x="63" y="168"/><int name="z" value="0"/><string name="_hash" value="c2ae25638277dfc2c2fe74e2993da20dc1b1a502d05ca1569f3d0d9933f2929d"/></canvas><canvas name="5" width="141" height="174"><vector name="origin" x="63" y="169"/><int name="z" value="0"/><string name="_hash" value="09c6977e0d14c8fd7ccd82da1beb402401b7122393a66ff9cc65a3318fc8bc3d"/></canvas><canvas name="6" width="141" height="174"><vector name="origin" x="63" y="170"/><int name="z" value="0"/><string name="_hash" value="ebfdf40863b2e2cc8eac629eb62c2078c74cc450ac3ab96f381f3cfc1549c4dc"/></canvas><canvas name="7" width="141" height="176"><vector name="origin" x="63" y="171"/><int name="z" value="0"/><string name="_hash" value="55ce226ae43b09737c4a1b40a18bb96fe0607064e4f87fd7e952ef6b0eb58391"/></canvas><canvas name="8" width="140" height="177"><vector name="origin" x="63" y="172"/><int name="z" value="0"/><string name="_hash" value="78bf3a51a44b10d558e792898156100ca122a54b8d5298eec5e0d005d48c9fd2"/></canvas><canvas name="9" width="144" height="178"><vector name="origin" x="66" y="173"/><int name="z" value="0"/><string name="_hash" value="ebbc7c8102cb632cca8cacf9d6af483d4422aa622e87bb2ce40cbdb7bc9582c6"/></canvas><canvas name="10" width="149" height="184"><vector name="origin" x="71" y="174"/><int name="z" value="0"/><string name="_hash" value="4d00bc36a5d72a922fa0b1904386e051f438e7a8e0ca86fbd0ddeb71f7d129a1"/></canvas><canvas name="11" width="144" height="180"><vector name="origin" x="66" y="175"/><int name="z" value="0"/><string name="_hash" value="f69e99905e7686da14155a47a27d0544b5f0c770d0e1d265b7f2e0165fe063dc"/></canvas><canvas name="12" width="140" height="179"><vector name="origin" x="63" y="174"/><int name="z" value="0"/><string name="_hash" value="58cecd60575358ce5d8d54cfdac52b2e46e71ab7d57fe61708313a93561bac6a"/></canvas><canvas name="13" width="141" height="178"><vector name="origin" x="63" y="173"/><int name="z" value="0"/><string name="_hash" value="62f31aa09b9e794770429347c7a67e002abe1e01e2e07f2f462ac019ebcbdd02"/></canvas><canvas name="14" width="141" height="176"><vector name="origin" x="63" y="172"/><int name="z" value="0"/><string name="_hash" value="4465b7f310e9741386da7176e199fd1fc68524063653c6878ee9debf360ca561"/></canvas><canvas name="15" width="141" height="176"><vector name="origin" x="63" y="171"/><int name="z" value="0"/><string name="_hash" value="9d90aac5270503bf1cd5c826ca43aaf53b30e640d902f65dc5bc156370553998"/></canvas></imgdir><imgdir name="action"><canvas name="0" width="140" height="175"><vector name="origin" x="63" y="170"/><int name="z" value="0"/><string name="_hash" value="2c6c4b3b901ad8d6bda638ef29992f69cf42a68ff30f316211ff1b325dbb58c7"/></canvas><canvas name="1" width="141" height="174"><vector name="origin" x="63" y="169"/><int name="z" value="0"/><string name="_hash" value="1591a9efb4bb73f04b0cdd5377e1e3abdcf1ec61441499590cb92f449a6ee33e"/></canvas><canvas name="2" width="141" height="172"><vector name="origin" x="63" y="168"/><int name="z" value="0"/><string name="_hash" value="72de98a8ef8dfa52fbd7dc72226822a141ac8f3cc92cb78b52052f5c94b1ebe2"/></canvas><canvas name="3" width="141" height="172"><vector name="origin" x="63" y="167"/><int name="z" value="0"/><string name="_hash" value="6e887dfdfc46fd2d17ec7738d7add2737e8f8b6cbeb11499268bf207fa24a2d2"/></canvas><canvas name="4" width="140" height="173"><vector name="origin" x="63" y="168"/><int name="z" value="0"/><string name="_hash" value="a36a9c6e6ff951bbab8c8dda74f03de40c1fd8c5c55f3702aeb3d175be705b72"/></canvas><canvas name="5" width="141" height="174"><vector name="origin" x="63" y="169"/><int name="z" value="0"/><string name="_hash" value="75109e060f80baf8beb4752b216419a81cff6d2505729762cf506dbac38392b7"/></canvas><canvas name="6" width="141" height="174"><vector name="origin" x="63" y="170"/><int name="z" value="0"/><string name="_hash" value="52ebf185d959c3bd4f71a34ced973c759d50dc7f768f7a6d8bdee4a12f698115"/></canvas><canvas name="7" width="141" height="176"><vector name="origin" x="63" y="171"/><int name="z" value="0"/><string name="_hash" value="7c379e404244f40167082c223e269642efbd0c09ed6f3e83582d7ac8f640b38b"/></canvas><canvas name="8" width="140" height="177"><vector name="origin" x="63" y="172"/><int name="z" value="0"/><string name="_hash" value="66601c89882000f58eb2af9cf9b0702a9066747d13eb6aea01ba6a8b8f20b32d"/></canvas><canvas name="9" width="144" height="178"><vector name="origin" x="66" y="173"/><int name="z" value="0"/><string name="_hash" value="b12c2fffd9e7ace2eda26f9c94180b3e22d0e8a915c5ff5fa6d88cc016d4d46b"/></canvas><canvas name="10" width="149" height="184"><vector name="origin" x="71" y="174"/><int name="z" value="0"/><string name="_hash" value="a8755b01304ddd0c5908decedd346d83b001dfdcf97e1bb93493464b0c932c61"/></canvas><canvas name="11" width="144" height="180"><vector name="origin" x="66" y="175"/><int name="z" value="0"/><string name="_hash" value="c5a9be47f27316b80bc8d8fcb84362f160892c7bf9a500daa7c3234550a5ce6d"/></canvas><canvas name="12" width="140" height="179"><vector name="origin" x="63" y="174"/><int name="z" value="0"/><string name="_hash" value="60ec9299aaedb1b0f4cb6e43119b52dbbc9dac10e8e291830d982cc684e334b6"/></canvas><canvas name="13" width="141" height="178"><vector name="origin" x="63" y="173"/><int name="z" value="0"/><string name="_hash" value="fb1095ca90e67bff7250ec9c18c86e3a2d79eb3606dda47fc7ba0efd38dd0509"/></canvas><canvas name="14" width="141" height="176"><vector name="origin" x="63" y="172"/><int name="z" value="0"/><string name="_hash" value="a3463d8fd5687c0cb54c5d92067d579c7b742f73f439bc7f9575707704aff5ac"/></canvas><canvas name="15" width="141" height="176"><vector name="origin" x="63" y="171"/><int name="z" value="0"/><string name="_hash" value="f2272210425880f743a8e894e5f8beb403ae119bca19839a2b7a0ab1be97d35a"/></canvas></imgdir><imgdir name="condition1"><imgdir name="stand"><canvas name="0" width="1" height="1"><vector name="origin" x="63" y="170"/><int name="z" value="0"/><string name="_inlink" value="stand/0"/></canvas><canvas name="1" width="1" height="1"><vector name="origin" x="63" y="169"/><int name="z" value="0"/><string name="_inlink" value="stand/1"/></canvas><canvas name="2" width="1" height="1"><vector name="origin" x="63" y="168"/><int name="z" value="0"/><string name="_inlink" value="stand/2"/></canvas><canvas name="3" width="1" height="1"><vector name="origin" x="63" y="167"/><int name="z" value="0"/><string name="_inlink" value="stand/3"/></canvas><canvas name="4" width="1" height="1"><vector name="origin" x="63" y="168"/><int name="z" value="0"/><string name="_inlink" value="stand/4"/></canvas><canvas name="5" width="1" height="1"><vector name="origin" x="63" y="169"/><int name="z" value="0"/><string name="_inlink" value="stand/5"/></canvas><canvas name="6" width="1" height="1"><vector name="origin" x="63" y="170"/><int name="z" value="0"/><string name="_inlink" value="stand/6"/></canvas><canvas name="7" width="1" height="1"><vector name="origin" x="63" y="171"/><int name="z" value="0"/><string name="_inlink" value="stand/7"/></canvas><canvas name="8" width="1" height="1"><vector name="origin" x="63" y="172"/><int name="z" value="0"/><string name="_inlink" value="stand/8"/></canvas><canvas name="9" width="1" height="1"><vector name="origin" x="66" y="173"/><int name="z" value="0"/><string name="_inlink" value="stand/9"/></canvas><canvas name="10" width="1" height="1"><vector name="origin" x="71" y="174"/><int name="z" value="0"/><string name="_inlink" value="stand/10"/></canvas><canvas name="11" width="1" height="1"><vector name="origin" x="66" y="175"/><int name="z" value="0"/><string name="_inlink" value="stand/11"/></canvas><canvas name="12" width="1" height="1"><vector name="origin" x="63" y="174"/><int name="z" value="0"/><string name="_inlink" value="stand/12"/></canvas><canvas name="13" width="1" height="1"><vector name="origin" x="63" y="173"/><int name="z" value="0"/><string name="_inlink" value="stand/13"/></canvas><canvas name="14" width="1" height="1"><vector name="origin" x="63" y="172"/><int name="z" value="0"/><string name="_inlink" value="stand/14"/></canvas><canvas name="15" width="1" height="1"><vector name="origin" x="63" y="171"/><int name="z" value="0"/><string name="_inlink" value="stand/15"/></canvas></imgdir><imgdir name="action"><canvas name="0" width="1" height="1"><vector name="origin" x="63" y="170"/><int name="z" value="0"/><string name="_inlink" value="action/0"/></canvas><canvas name="1" width="1" height="1"><vector name="origin" x="63" y="169"/><int name="z" value="0"/><string name="_inlink" value="action/1"/></canvas><canvas name="2" width="1" height="1"><vector name="origin" x="63" y="168"/><int name="z" value="0"/><string name="_inlink" value="action/2"/></canvas><canvas name="3" width="1" height="1"><vector name="origin" x="63" y="167"/><int name="z" value="0"/><string name="_inlink" value="action/3"/></canvas><canvas name="4" width="1" height="1"><vector name="origin" x="63" y="168"/><int name="z" value="0"/><string name="_inlink" value="action/4"/></canvas><canvas name="5" width="1" height="1"><vector name="origin" x="63" y="169"/><int name="z" value="0"/><string name="_inlink" value="action/5"/></canvas><canvas name="6" width="1" height="1"><vector name="origin" x="63" y="170"/><int name="z" value="0"/><string name="_inlink" value="action/6"/></canvas><canvas name="7" width="1" height="1"><vector name="origin" x="63" y="171"/><int name="z" value="0"/><string name="_inlink" value="action/7"/></canvas><canvas name="8" width="1" height="1"><vector name="origin" x="63" y="172"/><int name="z" value="0"/><string name="_inlink" value="action/8"/></canvas><canvas name="9" width="1" height="1"><vector name="origin" x="66" y="173"/><int name="z" value="0"/><string name="_inlink" value="action/9"/></canvas><canvas name="10" width="1" height="1"><vector name="origin" x="71" y="174"/><int name="z" value="0"/><string name="_inlink" value="action/10"/></canvas><canvas name="11" width="1" height="1"><vector name="origin" x="66" y="175"/><int name="z" value="0"/><string name="_inlink" value="action/11"/></canvas><canvas name="12" width="1" height="1"><vector name="origin" x="63" y="174"/><int name="z" value="0"/><string name="_inlink" value="action/12"/></canvas><canvas name="13" width="1" height="1"><vector name="origin" x="63" y="173"/><int name="z" value="0"/><string name="_inlink" value="action/13"/></canvas><canvas name="14" width="1" height="1"><vector name="origin" x="63" y="172"/><int name="z" value="0"/><string name="_inlink" value="action/14"/></canvas><canvas name="15" width="1" height="1"><vector name="origin" x="63" y="171"/><int name="z" value="0"/><string name="_inlink" value="action/15"/></canvas></imgdir><int name="hide" value="1"/><string name="dateStart" value="202009010000"/><string name="dateEnd" value="202011180000"/></imgdir></imgdir>