<?xml version="1.0" encoding="UTF-8" standalone="yes"?>
<imgdir name="00012029.img">
<imgdir name="info">
<string name="islot" value="Hd"/>
<string name="vslot" value="Hd"/>
<int name="cash" value="0"/>
</imgdir>
<imgdir name="front">
<canvas name="head" width="35" height="35">
<vector name="origin" x="18" y="17"/>
<imgdir name="map">
<vector name="neck" x="0" y="15"/>
<vector name="earOverHead" x="15" y="10"/>
<vector name="earBelowHead" x="-17" y="9"/>
<vector name="brow" x="-4" y="-5"/>
</imgdir>
<string name="z" value="head"/>
<string name="group" value="skin"/>
<string name="_hash" value="c5d3c47bec783d789762772961327208c61d60a9cca7e207b0abc55ffbfe3824"/>
</canvas>
<canvas name="humanEar" width="39" height="11">
<vector name="origin" x="19" y="-2"/>
<imgdir name="map">
<vector name="neck" x="0" y="15"/>
<vector name="earOverHead" x="15" y="10"/>
<vector name="earBelowHead" x="-17" y="9"/>
<vector name="brow" x="-4" y="-5"/>
</imgdir>
<string name="z" value="hairShade"/>
<string name="group" value="skin"/>
<string name="_hash" value="116cc110a0b186707b6d95de7d2f5b616bc8d8abe21d8bd3d57250c4f6119e0d"/>
</canvas>
<canvas name="ear" width="47" height="12">
<vector name="origin" x="23" y="-1"/>
<imgdir name="map">
<vector name="neck" x="0" y="15"/>
<vector name="earOverHead" x="15" y="10"/>
<vector name="earBelowHead" x="-17" y="9"/>
<vector name="brow" x="-4" y="-5"/>
</imgdir>
<string name="z" value="accessoryOverHair"/>
<string name="group" value="skin"/>
<string name="_hash" value="073fb974ec43729f053e51e857b74aee9d5a64e1266c463e3032f17001f8a1b1"/>
</canvas>
<canvas name="lefEar" width="53" height="10">
<vector name="origin" x="26" y="-3"/>
<imgdir name="map">
<vector name="neck" x="0" y="15"/>
<vector name="earOverHead" x="15" y="10"/>
<vector name="earBelowHead" x="-17" y="9"/>
<vector name="brow" x="-4" y="-5"/>
</imgdir>
<string name="z" value="accessoryOverHair"/>
<string name="group" value="skin"/>
<string name="_hash" value="7d5d14f452be85fd58953802a462f5c689e28659238d35a2a918db39e84e8abf"/>
</canvas>
<canvas name="highlefEar" width="49" height="10">
<vector name="origin" x="24" y="-3"/>
<imgdir name="map">
<vector name="neck" x="0" y="15"/>
<vector name="earOverHead" x="15" y="10"/>
<vector name="earBelowHead" x="-17" y="9"/>
<vector name="brow" x="-4" y="-5"/>
</imgdir>
<string name="z" value="accessoryOverHair"/>
<string name="group" value="skin"/>
<string name="_hash" value="611fcd6e019e9f27f4cb1ccd657594ceebf577f0b98c1febb1a8f23dfc32b20d"/>
</canvas>
</imgdir>
<imgdir name="back">
<canvas name="head" width="41" height="35">
<vector name="origin" x="20" y="17"/>
<imgdir name="map">
<vector name="neck" x="0" y="15"/>
<vector name="brow" x="-4" y="-5"/>
</imgdir>
<string name="z" value="backHead"/>
<string name="group" value="skin"/>
<string name="_hash" value="87e0500a81c359e3e1e1d752d4810954a8afa478dfd61a1681f4661ec2ea10c4"/>
</canvas>
<canvas name="ear" width="49" height="11">
<vector name="origin" x="24" y="-1"/>
<imgdir name="map">
<vector name="neck" x="0" y="15"/>
<vector name="brow" x="-4" y="-5"/>
</imgdir>
<string name="z" value="backAccessoryOverHead"/>
<string name="group" value="skin"/>
<string name="_hash" value="844aea651e3600ea966c4d9fab9664b68bc1a1defd52dab3bcd8557e5a5ccf8f"/>
</canvas>
<canvas name="lefEar" width="59" height="11">
<vector name="origin" x="29" y="-1"/>
<imgdir name="map">
<vector name="neck" x="0" y="15"/>
<vector name="brow" x="-4" y="-5"/>
</imgdir>
<string name="z" value="backAccessoryOverHead"/>
<string name="group" value="skin"/>
<string name="_hash" value="3d072f66582749ad2dcad88f3566a9c1775a17108bb40af3a2e184933ea5a61c"/>
</canvas>
<canvas name="highlefEar" width="55" height="11">
<vector name="origin" x="27" y="-1"/>
<imgdir name="map">
<vector name="neck" x="0" y="15"/>
<vector name="brow" x="-4" y="-5"/>
</imgdir>
<string name="z" value="backAccessoryOverHead"/>
<string name="group" value="skin"/>
<string name="_hash" value="acefc739d463cf7fb4616105ce788b6a1c0e691ab8cabf8ef3c3bfffae159b84"/>
</canvas>
</imgdir>
<imgdir name="walk1">
<imgdir name="0">
<uol name="head" value="../../front/head"/>
<uol name="ear" value="../../front/ear"/>
<uol name="lefEar" value="../../front/lefEar"/>
<uol name="highlefEar" value="../../front/highlefEar"/>
<uol name="humanEar" value="../../front/humanEar"/>
</imgdir>
<imgdir name="1">
<uol name="head" value="../../front/head"/>
<uol name="ear" value="../../front/ear"/>
<uol name="lefEar" value="../../front/lefEar"/>
<uol name="highlefEar" value="../../front/highlefEar"/>
<uol name="humanEar" value="../../front/humanEar"/>
</imgdir>
<imgdir name="2">
<uol name="head" value="../../front/head"/>
<uol name="ear" value="../../front/ear"/>
<uol name="lefEar" value="../../front/lefEar"/>
<uol name="highlefEar" value="../../front/highlefEar"/>
<uol name="humanEar" value="../../front/humanEar"/>
</imgdir>
<imgdir name="3">
<uol name="head" value="../../front/head"/>
<uol name="ear" value="../../front/ear"/>
<uol name="lefEar" value="../../front/lefEar"/>
<uol name="highlefEar" value="../../front/highlefEar"/>
<uol name="humanEar" value="../../front/humanEar"/>
</imgdir>
</imgdir>
<imgdir name="walk2">
<imgdir name="0">
<uol name="head" value="../../front/head"/>
<uol name="ear" value="../../front/ear"/>
<uol name="lefEar" value="../../front/lefEar"/>
<uol name="highlefEar" value="../../front/highlefEar"/>
<uol name="humanEar" value="../../front/humanEar"/>
</imgdir>
<imgdir name="1">
<uol name="head" value="../../front/head"/>
<uol name="ear" value="../../front/ear"/>
<uol name="lefEar" value="../../front/lefEar"/>
<uol name="highlefEar" value="../../front/highlefEar"/>
<uol name="humanEar" value="../../front/humanEar"/>
</imgdir>
<imgdir name="2">
<uol name="head" value="../../front/head"/>
<uol name="ear" value="../../front/ear"/>
<uol name="lefEar" value="../../front/lefEar"/>
<uol name="highlefEar" value="../../front/highlefEar"/>
<uol name="humanEar" value="../../front/humanEar"/>
</imgdir>
<imgdir name="3">
<uol name="head" value="../../front/head"/>
<uol name="ear" value="../../front/ear"/>
<uol name="lefEar" value="../../front/lefEar"/>
<uol name="highlefEar" value="../../front/highlefEar"/>
<uol name="humanEar" value="../../front/humanEar"/>
</imgdir>
</imgdir>
<imgdir name="stand1">
<imgdir name="0">
<uol name="head" value="../../front/head"/>
<uol name="ear" value="../../front/ear"/>
<uol name="lefEar" value="../../front/lefEar"/>
<uol name="highlefEar" value="../../front/highlefEar"/>
<uol name="humanEar" value="../../front/humanEar"/>
</imgdir>
<imgdir name="1">
<uol name="head" value="../../front/head"/>
<uol name="ear" value="../../front/ear"/>
<uol name="lefEar" value="../../front/lefEar"/>
<uol name="highlefEar" value="../../front/highlefEar"/>
<uol name="humanEar" value="../../front/humanEar"/>
</imgdir>
<imgdir name="2">
<uol name="head" value="../../front/head"/>
<uol name="ear" value="../../front/ear"/>
<uol name="lefEar" value="../../front/lefEar"/>
<uol name="highlefEar" value="../../front/highlefEar"/>
<uol name="humanEar" value="../../front/humanEar"/>
</imgdir>
</imgdir>
<imgdir name="stand2">
<imgdir name="0">
<uol name="head" value="../../front/head"/>
<uol name="ear" value="../../front/ear"/>
<uol name="lefEar" value="../../front/lefEar"/>
<uol name="highlefEar" value="../../front/highlefEar"/>
<uol name="humanEar" value="../../front/humanEar"/>
</imgdir>
<imgdir name="1">
<uol name="head" value="../../front/head"/>
<uol name="ear" value="../../front/ear"/>
<uol name="lefEar" value="../../front/lefEar"/>
<uol name="highlefEar" value="../../front/highlefEar"/>
<uol name="humanEar" value="../../front/humanEar"/>
</imgdir>
<imgdir name="2">
<uol name="head" value="../../front/head"/>
<uol name="ear" value="../../front/ear"/>
<uol name="lefEar" value="../../front/lefEar"/>
<uol name="highlefEar" value="../../front/highlefEar"/>
<uol name="humanEar" value="../../front/humanEar"/>
</imgdir>
</imgdir>
<imgdir name="alert">
<imgdir name="0">
<uol name="head" value="../../front/head"/>
<uol name="ear" value="../../front/ear"/>
<uol name="lefEar" value="../../front/lefEar"/>
<uol name="highlefEar" value="../../front/highlefEar"/>
<uol name="humanEar" value="../../front/humanEar"/>
</imgdir>
<imgdir name="1">
<uol name="head" value="../../front/head"/>
<uol name="ear" value="../../front/ear"/>
<uol name="lefEar" value="../../front/lefEar"/>
<uol name="highlefEar" value="../../front/highlefEar"/>
<uol name="humanEar" value="../../front/humanEar"/>
</imgdir>
<imgdir name="2">
<uol name="head" value="../../front/head"/>
<uol name="ear" value="../../front/ear"/>
<uol name="lefEar" value="../../front/lefEar"/>
<uol name="highlefEar" value="../../front/highlefEar"/>
<uol name="humanEar" value="../../front/humanEar"/>
</imgdir>
</imgdir>
<imgdir name="swingO1">
<imgdir name="0">
<uol name="head" value="../../front/head"/>
<uol name="ear" value="../../front/ear"/>
<uol name="lefEar" value="../../front/lefEar"/>
<uol name="highlefEar" value="../../front/highlefEar"/>
<uol name="humanEar" value="../../front/humanEar"/>
</imgdir>
<imgdir name="1">
<uol name="head" value="../../front/head"/>
<uol name="ear" value="../../front/ear"/>
<uol name="lefEar" value="../../front/lefEar"/>
<uol name="highlefEar" value="../../front/highlefEar"/>
<uol name="humanEar" value="../../front/humanEar"/>
</imgdir>
<imgdir name="2">
<uol name="head" value="../../front/head"/>
<uol name="ear" value="../../front/ear"/>
<uol name="lefEar" value="../../front/lefEar"/>
<uol name="highlefEar" value="../../front/highlefEar"/>
<uol name="humanEar" value="../../front/humanEar"/>
</imgdir>
</imgdir>
<imgdir name="swingO2">
<imgdir name="0">
<uol name="head" value="../../front/head"/>
<uol name="ear" value="../../front/ear"/>
<uol name="lefEar" value="../../front/lefEar"/>
<uol name="highlefEar" value="../../front/highlefEar"/>
<uol name="humanEar" value="../../front/humanEar"/>
</imgdir>
<imgdir name="1">
<uol name="head" value="../../front/head"/>
<uol name="ear" value="../../front/ear"/>
<uol name="lefEar" value="../../front/lefEar"/>
<uol name="highlefEar" value="../../front/highlefEar"/>
<uol name="humanEar" value="../../front/humanEar"/>
</imgdir>
<imgdir name="2">
<uol name="head" value="../../front/head"/>
<uol name="ear" value="../../front/ear"/>
<uol name="lefEar" value="../../front/lefEar"/>
<uol name="highlefEar" value="../../front/highlefEar"/>
<uol name="humanEar" value="../../front/humanEar"/>
</imgdir>
</imgdir>
<imgdir name="swingO3">
<imgdir name="0">
<uol name="head" value="../../front/head"/>
<uol name="ear" value="../../front/ear"/>
<uol name="lefEar" value="../../front/lefEar"/>
<uol name="highlefEar" value="../../front/highlefEar"/>
<uol name="humanEar" value="../../front/humanEar"/>
</imgdir>
<imgdir name="1">
<uol name="head" value="../../front/head"/>
<uol name="ear" value="../../front/ear"/>
<uol name="lefEar" value="../../front/lefEar"/>
<uol name="highlefEar" value="../../front/highlefEar"/>
<uol name="humanEar" value="../../front/humanEar"/>
</imgdir>
<imgdir name="2">
<uol name="head" value="../../front/head"/>
<uol name="ear" value="../../front/ear"/>
<uol name="lefEar" value="../../front/lefEar"/>
<uol name="highlefEar" value="../../front/highlefEar"/>
<uol name="humanEar" value="../../front/humanEar"/>
</imgdir>
</imgdir>
<imgdir name="swingOF">
<imgdir name="0">
<uol name="head" value="../../front/head"/>
<uol name="ear" value="../../front/ear"/>
<uol name="lefEar" value="../../front/lefEar"/>
<uol name="highlefEar" value="../../front/highlefEar"/>
<uol name="humanEar" value="../../front/humanEar"/>
</imgdir>
<imgdir name="1">
<uol name="head" value="../../back/head"/>
<uol name="ear" value="../../back/ear"/>
<uol name="lefEar" value="../../back/lefEar"/>
<uol name="highlefEar" value="../../back/highlefEar"/>
</imgdir>
<imgdir name="2">
<uol name="head" value="../../front/head"/>
<uol name="ear" value="../../front/ear"/>
<uol name="lefEar" value="../../front/lefEar"/>
<uol name="highlefEar" value="../../front/highlefEar"/>
<uol name="humanEar" value="../../front/humanEar"/>
</imgdir>
<imgdir name="3">
<uol name="head" value="../../front/head"/>
<uol name="ear" value="../../front/ear"/>
<uol name="lefEar" value="../../front/lefEar"/>
<uol name="highlefEar" value="../../front/highlefEar"/>
<uol name="humanEar" value="../../front/humanEar"/>
</imgdir>
</imgdir>
<imgdir name="swingT1">
<imgdir name="0">
<uol name="head" value="../../front/head"/>
<uol name="ear" value="../../front/ear"/>
<uol name="lefEar" value="../../front/lefEar"/>
<uol name="highlefEar" value="../../front/highlefEar"/>
<uol name="humanEar" value="../../front/humanEar"/>
</imgdir>
<imgdir name="1">
<uol name="head" value="../../front/head"/>
<uol name="ear" value="../../front/ear"/>
<uol name="lefEar" value="../../front/lefEar"/>
<uol name="highlefEar" value="../../front/highlefEar"/>
<uol name="humanEar" value="../../front/humanEar"/>
</imgdir>
<imgdir name="2">
<uol name="head" value="../../front/head"/>
<uol name="ear" value="../../front/ear"/>
<uol name="lefEar" value="../../front/lefEar"/>
<uol name="highlefEar" value="../../front/highlefEar"/>
<uol name="humanEar" value="../../front/humanEar"/>
</imgdir>
</imgdir>
<imgdir name="swingT2">
<imgdir name="0">
<uol name="head" value="../../front/head"/>
<uol name="ear" value="../../front/ear"/>
<uol name="lefEar" value="../../front/lefEar"/>
<uol name="highlefEar" value="../../front/highlefEar"/>
<uol name="humanEar" value="../../front/humanEar"/>
</imgdir>
<imgdir name="1">
<uol name="head" value="../../front/head"/>
<uol name="ear" value="../../front/ear"/>
<uol name="lefEar" value="../../front/lefEar"/>
<uol name="highlefEar" value="../../front/highlefEar"/>
<uol name="humanEar" value="../../front/humanEar"/>
</imgdir>
<imgdir name="2">
<uol name="head" value="../../front/head"/>
<uol name="ear" value="../../front/ear"/>
<uol name="lefEar" value="../../front/lefEar"/>
<uol name="highlefEar" value="../../front/highlefEar"/>
<uol name="humanEar" value="../../front/humanEar"/>
</imgdir>
</imgdir>
<imgdir name="swingT3">
<imgdir name="0">
<uol name="head" value="../../front/head"/>
<uol name="ear" value="../../front/ear"/>
<uol name="lefEar" value="../../front/lefEar"/>
<uol name="highlefEar" value="../../front/highlefEar"/>
<uol name="humanEar" value="../../front/humanEar"/>
</imgdir>
<imgdir name="1">
<uol name="head" value="../../front/head"/>
<uol name="ear" value="../../front/ear"/>
<uol name="lefEar" value="../../front/lefEar"/>
<uol name="highlefEar" value="../../front/highlefEar"/>
<uol name="humanEar" value="../../front/humanEar"/>
</imgdir>
<imgdir name="2">
<uol name="head" value="../../front/head"/>
<uol name="ear" value="../../front/ear"/>
<uol name="lefEar" value="../../front/lefEar"/>
<uol name="highlefEar" value="../../front/highlefEar"/>
<uol name="humanEar" value="../../front/humanEar"/>
</imgdir>
</imgdir>
<imgdir name="swingTF">
<imgdir name="0">
<uol name="head" value="../../back/head"/>
<uol name="ear" value="../../back/ear"/>
<uol name="lefEar" value="../../back/lefEar"/>
<uol name="highlefEar" value="../../back/highlefEar"/>
</imgdir>
<imgdir name="1">
<uol name="head" value="../../front/head"/>
<uol name="ear" value="../../front/ear"/>
<uol name="lefEar" value="../../front/lefEar"/>
<uol name="highlefEar" value="../../front/highlefEar"/>
<uol name="humanEar" value="../../front/humanEar"/>
</imgdir>
<imgdir name="2">
<uol name="head" value="../../front/head"/>
<uol name="ear" value="../../front/ear"/>
<uol name="lefEar" value="../../front/lefEar"/>
<uol name="highlefEar" value="../../front/highlefEar"/>
<uol name="humanEar" value="../../front/humanEar"/>
</imgdir>
<imgdir name="3">
<uol name="head" value="../../front/head"/>
<uol name="ear" value="../../front/ear"/>
<uol name="lefEar" value="../../front/lefEar"/>
<uol name="highlefEar" value="../../front/highlefEar"/>
<uol name="humanEar" value="../../front/humanEar"/>
</imgdir>
</imgdir>
<imgdir name="swingP1">
<imgdir name="0">
<uol name="head" value="../../front/head"/>
<uol name="ear" value="../../front/ear"/>
<uol name="lefEar" value="../../front/lefEar"/>
<uol name="highlefEar" value="../../front/highlefEar"/>
<uol name="humanEar" value="../../front/humanEar"/>
</imgdir>
<imgdir name="1">
<uol name="head" value="../../front/head"/>
<uol name="ear" value="../../front/ear"/>
<uol name="lefEar" value="../../front/lefEar"/>
<uol name="highlefEar" value="../../front/highlefEar"/>
<uol name="humanEar" value="../../front/humanEar"/>
</imgdir>
<imgdir name="2">
<uol name="head" value="../../front/head"/>
<uol name="ear" value="../../front/ear"/>
<uol name="lefEar" value="../../front/lefEar"/>
<uol name="highlefEar" value="../../front/highlefEar"/>
<uol name="humanEar" value="../../front/humanEar"/>
</imgdir>
</imgdir>
<imgdir name="swingP2">
<imgdir name="0">
<uol name="head" value="../../front/head"/>
<uol name="ear" value="../../front/ear"/>
<uol name="lefEar" value="../../front/lefEar"/>
<uol name="highlefEar" value="../../front/highlefEar"/>
<uol name="humanEar" value="../../front/humanEar"/>
</imgdir>
<imgdir name="1">
<uol name="head" value="../../front/head"/>
<uol name="ear" value="../../front/ear"/>
<uol name="lefEar" value="../../front/lefEar"/>
<uol name="highlefEar" value="../../front/highlefEar"/>
<uol name="humanEar" value="../../front/humanEar"/>
</imgdir>
<imgdir name="2">
<uol name="head" value="../../front/head"/>
<uol name="ear" value="../../front/ear"/>
<uol name="lefEar" value="../../front/lefEar"/>
<uol name="highlefEar" value="../../front/highlefEar"/>
<uol name="humanEar" value="../../front/humanEar"/>
</imgdir>
</imgdir>
<imgdir name="swingPF">
<imgdir name="0">
<uol name="head" value="../../front/head"/>
<uol name="ear" value="../../front/ear"/>
<uol name="lefEar" value="../../front/lefEar"/>
<uol name="highlefEar" value="../../front/highlefEar"/>
<uol name="humanEar" value="../../front/humanEar"/>
</imgdir>
<imgdir name="1">
<uol name="head" value="../../front/head"/>
<uol name="ear" value="../../front/ear"/>
<uol name="lefEar" value="../../front/lefEar"/>
<uol name="highlefEar" value="../../front/highlefEar"/>
<uol name="humanEar" value="../../front/humanEar"/>
</imgdir>
<imgdir name="2">
<uol name="head" value="../../front/head"/>
<uol name="ear" value="../../front/ear"/>
<uol name="lefEar" value="../../front/lefEar"/>
<uol name="highlefEar" value="../../front/highlefEar"/>
<uol name="humanEar" value="../../front/humanEar"/>
</imgdir>
<imgdir name="3">
<uol name="head" value="../../front/head"/>
<uol name="ear" value="../../front/ear"/>
<uol name="lefEar" value="../../front/lefEar"/>
<uol name="highlefEar" value="../../front/highlefEar"/>
<uol name="humanEar" value="../../front/humanEar"/>
</imgdir>
</imgdir>
<imgdir name="stabO1">
<imgdir name="0">
<uol name="head" value="../../front/head"/>
<uol name="ear" value="../../front/ear"/>
<uol name="lefEar" value="../../front/lefEar"/>
<uol name="highlefEar" value="../../front/highlefEar"/>
<uol name="humanEar" value="../../front/humanEar"/>
</imgdir>
<imgdir name="1">
<uol name="head" value="../../front/head"/>
<uol name="ear" value="../../front/ear"/>
<uol name="lefEar" value="../../front/lefEar"/>
<uol name="highlefEar" value="../../front/highlefEar"/>
<uol name="humanEar" value="../../front/humanEar"/>
</imgdir>
</imgdir>
<imgdir name="stabO2">
<imgdir name="0">
<uol name="head" value="../../front/head"/>
<uol name="ear" value="../../front/ear"/>
<uol name="lefEar" value="../../front/lefEar"/>
<uol name="highlefEar" value="../../front/highlefEar"/>
<uol name="humanEar" value="../../front/humanEar"/>
</imgdir>
<imgdir name="1">
<uol name="head" value="../../front/head"/>
<uol name="ear" value="../../front/ear"/>
<uol name="lefEar" value="../../front/lefEar"/>
<uol name="highlefEar" value="../../front/highlefEar"/>
<uol name="humanEar" value="../../front/humanEar"/>
</imgdir>
</imgdir>
<imgdir name="stabOF">
<imgdir name="0">
<uol name="head" value="../../front/head"/>
<uol name="ear" value="../../front/ear"/>
<uol name="lefEar" value="../../front/lefEar"/>
<uol name="highlefEar" value="../../front/highlefEar"/>
<uol name="humanEar" value="../../front/humanEar"/>
</imgdir>
<imgdir name="1">
<uol name="head" value="../../front/head"/>
<uol name="ear" value="../../front/ear"/>
<uol name="lefEar" value="../../front/lefEar"/>
<uol name="highlefEar" value="../../front/highlefEar"/>
<uol name="humanEar" value="../../front/humanEar"/>
</imgdir>
<imgdir name="2">
<uol name="head" value="../../front/head"/>
<uol name="ear" value="../../front/ear"/>
<uol name="lefEar" value="../../front/lefEar"/>
<uol name="highlefEar" value="../../front/highlefEar"/>
<uol name="humanEar" value="../../front/humanEar"/>
</imgdir>
</imgdir>
<imgdir name="stabT1">
<imgdir name="0">
<uol name="head" value="../../front/head"/>
<uol name="ear" value="../../front/ear"/>
<uol name="lefEar" value="../../front/lefEar"/>
<uol name="highlefEar" value="../../front/highlefEar"/>
<uol name="humanEar" value="../../front/humanEar"/>
</imgdir>
<imgdir name="1">
<uol name="head" value="../../front/head"/>
<uol name="ear" value="../../front/ear"/>
<uol name="lefEar" value="../../front/lefEar"/>
<uol name="highlefEar" value="../../front/highlefEar"/>
<uol name="humanEar" value="../../front/humanEar"/>
</imgdir>
<imgdir name="2">
<uol name="head" value="../../front/head"/>
<uol name="ear" value="../../front/ear"/>
<uol name="lefEar" value="../../front/lefEar"/>
<uol name="highlefEar" value="../../front/highlefEar"/>
<uol name="humanEar" value="../../front/humanEar"/>
</imgdir>
</imgdir>
<imgdir name="stabT2">
<imgdir name="0">
<uol name="head" value="../../front/head"/>
<uol name="ear" value="../../front/ear"/>
<uol name="lefEar" value="../../front/lefEar"/>
<uol name="highlefEar" value="../../front/highlefEar"/>
<uol name="humanEar" value="../../front/humanEar"/>
</imgdir>
<imgdir name="1">
<uol name="head" value="../../front/head"/>
<uol name="ear" value="../../front/ear"/>
<uol name="lefEar" value="../../front/lefEar"/>
<uol name="highlefEar" value="../../front/highlefEar"/>
<uol name="humanEar" value="../../front/humanEar"/>
</imgdir>
<imgdir name="2">
<uol name="head" value="../../front/head"/>
<uol name="ear" value="../../front/ear"/>
<uol name="lefEar" value="../../front/lefEar"/>
<uol name="highlefEar" value="../../front/highlefEar"/>
<uol name="humanEar" value="../../front/humanEar"/>
</imgdir>
</imgdir>
<imgdir name="stabTF">
<imgdir name="0">
<uol name="head" value="../../front/head"/>
<uol name="ear" value="../../front/ear"/>
<uol name="lefEar" value="../../front/lefEar"/>
<uol name="highlefEar" value="../../front/highlefEar"/>
<uol name="humanEar" value="../../front/humanEar"/>
</imgdir>
<imgdir name="1">
<uol name="head" value="../../front/head"/>
<uol name="ear" value="../../front/ear"/>
<uol name="lefEar" value="../../front/lefEar"/>
<uol name="highlefEar" value="../../front/highlefEar"/>
<uol name="humanEar" value="../../front/humanEar"/>
</imgdir>
<imgdir name="2">
<uol name="head" value="../../front/head"/>
<uol name="ear" value="../../front/ear"/>
<uol name="lefEar" value="../../front/lefEar"/>
<uol name="highlefEar" value="../../front/highlefEar"/>
<uol name="humanEar" value="../../front/humanEar"/>
</imgdir>
<imgdir name="3">
<uol name="head" value="../../front/head"/>
<uol name="ear" value="../../front/ear"/>
<uol name="lefEar" value="../../front/lefEar"/>
<uol name="highlefEar" value="../../front/highlefEar"/>
<uol name="humanEar" value="../../front/humanEar"/>
</imgdir>
</imgdir>
<imgdir name="shoot1">
<imgdir name="0">
<uol name="head" value="../../front/head"/>
<uol name="ear" value="../../front/ear"/>
<uol name="lefEar" value="../../front/lefEar"/>
<uol name="highlefEar" value="../../front/highlefEar"/>
<uol name="humanEar" value="../../front/humanEar"/>
</imgdir>
<imgdir name="1">
<uol name="head" value="../../front/head"/>
<uol name="ear" value="../../front/ear"/>
<uol name="lefEar" value="../../front/lefEar"/>
<uol name="highlefEar" value="../../front/highlefEar"/>
<uol name="humanEar" value="../../front/humanEar"/>
</imgdir>
<imgdir name="2">
<uol name="head" value="../../front/head"/>
<uol name="ear" value="../../front/ear"/>
<uol name="lefEar" value="../../front/lefEar"/>
<uol name="highlefEar" value="../../front/highlefEar"/>
<uol name="humanEar" value="../../front/humanEar"/>
</imgdir>
</imgdir>
<imgdir name="shoot2">
<imgdir name="0">
<uol name="head" value="../../front/head"/>
<uol name="ear" value="../../front/ear"/>
<uol name="lefEar" value="../../front/lefEar"/>
<uol name="highlefEar" value="../../front/highlefEar"/>
<uol name="humanEar" value="../../front/humanEar"/>
</imgdir>
<imgdir name="1">
<uol name="head" value="../../front/head"/>
<uol name="ear" value="../../front/ear"/>
<uol name="lefEar" value="../../front/lefEar"/>
<uol name="highlefEar" value="../../front/highlefEar"/>
<uol name="humanEar" value="../../front/humanEar"/>
</imgdir>
<imgdir name="2">
<uol name="head" value="../../front/head"/>
<uol name="ear" value="../../front/ear"/>
<uol name="lefEar" value="../../front/lefEar"/>
<uol name="highlefEar" value="../../front/highlefEar"/>
<uol name="humanEar" value="../../front/humanEar"/>
</imgdir>
<imgdir name="3">
<uol name="head" value="../../front/head"/>
<uol name="ear" value="../../front/ear"/>
<uol name="lefEar" value="../../front/lefEar"/>
<uol name="highlefEar" value="../../front/highlefEar"/>
<uol name="humanEar" value="../../front/humanEar"/>
</imgdir>
<imgdir name="4">
<uol name="head" value="../../front/head"/>
<uol name="ear" value="../../front/ear"/>
<uol name="lefEar" value="../../front/lefEar"/>
<uol name="highlefEar" value="../../front/highlefEar"/>
<uol name="humanEar" value="../../front/humanEar"/>
</imgdir>
</imgdir>
<imgdir name="shootF">
<imgdir name="0">
<uol name="head" value="../../front/head"/>
<uol name="ear" value="../../front/ear"/>
<uol name="lefEar" value="../../front/lefEar"/>
<uol name="highlefEar" value="../../front/highlefEar"/>
<uol name="humanEar" value="../../front/humanEar"/>
</imgdir>
<imgdir name="1">
<uol name="head" value="../../front/head"/>
<uol name="ear" value="../../front/ear"/>
<uol name="lefEar" value="../../front/lefEar"/>
<uol name="highlefEar" value="../../front/highlefEar"/>
<uol name="humanEar" value="../../front/humanEar"/>
</imgdir>
<imgdir name="2">
<uol name="head" value="../../front/head"/>
<uol name="ear" value="../../front/ear"/>
<uol name="lefEar" value="../../front/lefEar"/>
<uol name="highlefEar" value="../../front/highlefEar"/>
<uol name="humanEar" value="../../front/humanEar"/>
</imgdir>
</imgdir>
<imgdir name="proneStab">
<imgdir name="0">
<uol name="head" value="../../front/head"/>
<uol name="ear" value="../../front/ear"/>
<uol name="lefEar" value="../../front/lefEar"/>
<uol name="highlefEar" value="../../front/highlefEar"/>
<uol name="humanEar" value="../../front/humanEar"/>
</imgdir>
<imgdir name="1">
<uol name="head" value="../../front/head"/>
<uol name="ear" value="../../front/ear"/>
<uol name="lefEar" value="../../front/lefEar"/>
<uol name="highlefEar" value="../../front/highlefEar"/>
<uol name="humanEar" value="../../front/humanEar"/>
</imgdir>
</imgdir>
<imgdir name="prone">
<imgdir name="0">
<uol name="head" value="../../front/head"/>
<uol name="ear" value="../../front/ear"/>
<uol name="lefEar" value="../../front/lefEar"/>
<uol name="highlefEar" value="../../front/highlefEar"/>
<uol name="humanEar" value="../../front/humanEar"/>
</imgdir>
</imgdir>
<imgdir name="heal">
<imgdir name="0">
<uol name="head" value="../../front/head"/>
<uol name="ear" value="../../front/ear"/>
<uol name="lefEar" value="../../front/lefEar"/>
<uol name="highlefEar" value="../../front/highlefEar"/>
<uol name="humanEar" value="../../front/humanEar"/>
</imgdir>
<imgdir name="1">
<uol name="head" value="../../front/head"/>
<uol name="ear" value="../../front/ear"/>
<uol name="lefEar" value="../../front/lefEar"/>
<uol name="highlefEar" value="../../front/highlefEar"/>
<uol name="humanEar" value="../../front/humanEar"/>
</imgdir>
<imgdir name="2">
<uol name="head" value="../../front/head"/>
<uol name="ear" value="../../front/ear"/>
<uol name="lefEar" value="../../front/lefEar"/>
<uol name="highlefEar" value="../../front/highlefEar"/>
<uol name="humanEar" value="../../front/humanEar"/>
</imgdir>
</imgdir>
<imgdir name="fly">
<imgdir name="0">
<uol name="head" value="../../front/head"/>
<uol name="ear" value="../../front/ear"/>
<uol name="lefEar" value="../../front/lefEar"/>
<uol name="highlefEar" value="../../front/highlefEar"/>
<uol name="humanEar" value="../../front/humanEar"/>
</imgdir>
<imgdir name="1">
<uol name="head" value="../../front/head"/>
<uol name="ear" value="../../front/ear"/>
<uol name="lefEar" value="../../front/lefEar"/>
<uol name="highlefEar" value="../../front/highlefEar"/>
<uol name="humanEar" value="../../front/humanEar"/>
</imgdir>
</imgdir>
<imgdir name="jump">
<imgdir name="0">
<uol name="head" value="../../front/head"/>
<uol name="ear" value="../../front/ear"/>
<uol name="lefEar" value="../../front/lefEar"/>
<uol name="highlefEar" value="../../front/highlefEar"/>
<uol name="humanEar" value="../../front/humanEar"/>
</imgdir>
</imgdir>
<imgdir name="sit">
<imgdir name="0">
<uol name="head" value="../../front/head"/>
<uol name="ear" value="../../front/ear"/>
<uol name="lefEar" value="../../front/lefEar"/>
<uol name="highlefEar" value="../../front/highlefEar"/>
<uol name="humanEar" value="../../front/humanEar"/>
</imgdir>
</imgdir>
<imgdir name="ladder">
<imgdir name="0">
<uol name="head" value="../../back/head"/>
<uol name="ear" value="../../back/ear"/>
<uol name="lefEar" value="../../back/lefEar"/>
<uol name="highlefEar" value="../../back/highlefEar"/>
</imgdir>
<imgdir name="1">
<uol name="head" value="../../back/head"/>
<uol name="ear" value="../../back/ear"/>
<uol name="lefEar" value="../../back/lefEar"/>
<uol name="highlefEar" value="../../back/highlefEar"/>
</imgdir>
</imgdir>
<imgdir name="rope">
<imgdir name="0">
<uol name="head" value="../../back/head"/>
<uol name="ear" value="../../back/ear"/>
<uol name="lefEar" value="../../back/lefEar"/>
<uol name="highlefEar" value="../../back/highlefEar"/>
</imgdir>
<imgdir name="1">
<uol name="head" value="../../back/head"/>
<uol name="ear" value="../../back/ear"/>
<uol name="lefEar" value="../../back/lefEar"/>
<uol name="highlefEar" value="../../back/highlefEar"/>
</imgdir>
</imgdir>
<imgdir name="create2">
<imgdir name="0">
<uol name="head" value="../../front/head"/>
</imgdir>
<imgdir name="1">
<uol name="head" value="../../front/head"/>
</imgdir>
<imgdir name="2">
<uol name="head" value="../../front/head"/>
</imgdir>
<imgdir name="3">
<uol name="head" value="../../front/head"/>
</imgdir>
<imgdir name="4">
<uol name="head" value="../../front/head"/>
</imgdir>
<imgdir name="5">
<uol name="head" value="../../front/head"/>
</imgdir>
<imgdir name="6">
<uol name="head" value="../../front/head"/>
</imgdir>
<imgdir name="7">
<uol name="head" value="../../front/head"/>
</imgdir>
</imgdir>
<imgdir name="create2_s">
<imgdir name="0">
<uol name="head" value="../../front/head"/>
</imgdir>
</imgdir>
<imgdir name="create2_f">
<imgdir name="0">
<uol name="head" value="../../front/head"/>
</imgdir>
</imgdir>
<imgdir name="create3">
<imgdir name="0">
<uol name="head" value="../../front/head"/>
</imgdir>
<imgdir name="1">
<uol name="head" value="../../front/head"/>
</imgdir>
<imgdir name="2">
<uol name="head" value="../../front/head"/>
</imgdir>
<imgdir name="3">
<uol name="head" value="../../front/head"/>
</imgdir>
<imgdir name="4">
<uol name="head" value="../../front/head"/>
</imgdir>
<imgdir name="5">
<uol name="head" value="../../front/head"/>
</imgdir>
<imgdir name="6">
<uol name="head" value="../../front/head"/>
</imgdir>
<imgdir name="7">
<uol name="head" value="../../front/head"/>
</imgdir>
<imgdir name="8">
<uol name="head" value="../../front/head"/>
</imgdir>
<imgdir name="9">
<uol name="head" value="../../front/head"/>
</imgdir>
<imgdir name="10">
<uol name="head" value="../../front/head"/>
</imgdir>
<imgdir name="11">
<uol name="head" value="../../front/head"/>
</imgdir>
</imgdir>
<imgdir name="create3_s">
<imgdir name="0">
<uol name="head" value="../../front/head"/>
</imgdir>
</imgdir>
<imgdir name="create3_f">
<imgdir name="0">
<uol name="head" value="../../front/head"/>
</imgdir>
</imgdir>
<imgdir name="create4">
<imgdir name="0">
<uol name="head" value="../../front/head"/>
</imgdir>
<imgdir name="1">
<uol name="head" value="../../front/head"/>
</imgdir>
<imgdir name="2">
<uol name="head" value="../../front/head"/>
</imgdir>
<imgdir name="3">
<uol name="head" value="../../front/head"/>
</imgdir>
<imgdir name="4">
<uol name="head" value="../../front/head"/>
</imgdir>
<imgdir name="5">
<uol name="head" value="../../front/head"/>
</imgdir>
<imgdir name="6">
<uol name="head" value="../../front/head"/>
</imgdir>
<imgdir name="7">
<uol name="head" value="../../front/head"/>
</imgdir>
<imgdir name="8">
<uol name="head" value="../../front/head"/>
</imgdir>
<imgdir name="9">
<uol name="head" value="../../front/head"/>
</imgdir>
<imgdir name="10">
<uol name="head" value="../../front/head"/>
</imgdir>
<imgdir name="11">
<uol name="head" value="../../front/head"/>
</imgdir>
<imgdir name="12">
<uol name="head" value="../../front/head"/>
</imgdir>
<imgdir name="13">
<uol name="head" value="../../front/head"/>
</imgdir>
</imgdir>
<imgdir name="create4_s">
<imgdir name="0">
<uol name="head" value="../../front/head"/>
</imgdir>
</imgdir>
<imgdir name="create4_f">
<imgdir name="0">
<uol name="head" value="../../front/head"/>
</imgdir>
</imgdir>
<imgdir name="blink">
<imgdir name="0">
<canvas name="head" width="1" height="1">
<vector name="origin" x="19" y="17"/>
<imgdir name="map">
<vector name="neck" x="0" y="15"/>
<vector name="earOverHead" x="15" y="10"/>
<vector name="earBelowHead" x="-17" y="9"/>
<vector name="brow" x="-4" y="-5"/>
</imgdir>
<string name="z" value="head"/>
<string name="group" value="skin"/>
</canvas>
</imgdir>
</imgdir>
<imgdir name="hide">
<imgdir name="0">
<canvas name="head" width="1" height="1">
<vector name="origin" x="19" y="17"/>
<imgdir name="map">
<vector name="neck" x="0" y="15"/>
<vector name="earOverHead" x="15" y="10"/>
<vector name="earBelowHead" x="-17" y="9"/>
<vector name="brow" x="-4" y="-5"/>
</imgdir>
<string name="z" value="head"/>
<string name="group" value="skin"/>
</canvas>
</imgdir>
</imgdir>
<imgdir name="setitem3">
<imgdir name="0">
<uol name="head" value="../../front/head"/>
</imgdir>
<imgdir name="1">
<uol name="head" value="../../front/head"/>
</imgdir>
<imgdir name="2">
<uol name="head" value="../../front/head"/>
</imgdir>
<imgdir name="3">
<uol name="head" value="../../front/head"/>
</imgdir>
<imgdir name="4">
<uol name="head" value="../../front/head"/>
</imgdir>
<imgdir name="5">
<uol name="head" value="../../front/head"/>
</imgdir>
<imgdir name="6">
<uol name="head" value="../../blink/0/head"/>
</imgdir>
<imgdir name="7">
<uol name="head" value="../../blink/0/head"/>
</imgdir>
<imgdir name="8">
<uol name="head" value="../../front/head"/>
</imgdir>
<imgdir name="9">
<uol name="head" value="../../front/head"/>
</imgdir>
<imgdir name="10">
<uol name="head" value="../../front/head"/>
</imgdir>
<imgdir name="11">
<uol name="head" value="../../front/head"/>
</imgdir>
<imgdir name="12">
<uol name="head" value="../../front/head"/>
</imgdir>
<imgdir name="13">
<uol name="head" value="../../front/head"/>
</imgdir>
<imgdir name="14">
<uol name="head" value="../../front/head"/>
</imgdir>
<imgdir name="15">
<uol name="head" value="../../front/head"/>
</imgdir>
<imgdir name="16">
<uol name="head" value="../../front/head"/>
</imgdir>
<imgdir name="17">
<uol name="head" value="../../front/head"/>
</imgdir>
<imgdir name="18">
<uol name="head" value="../../front/head"/>
</imgdir>
<imgdir name="19">
<uol name="head" value="../../front/head"/>
</imgdir>
<imgdir name="20">
<uol name="head" value="../../front/head"/>
</imgdir>
<imgdir name="21">
<uol name="head" value="../../front/head"/>
</imgdir>
<imgdir name="22">
<uol name="head" value="../../front/head"/>
</imgdir>
<imgdir name="23">
<uol name="head" value="../../front/head"/>
</imgdir>
<imgdir name="24">
<uol name="head" value="../../front/head"/>
</imgdir>
<imgdir name="25">
<uol name="head" value="../../front/head"/>
</imgdir>
<imgdir name="26">
<uol name="head" value="../../front/head"/>
</imgdir>
</imgdir>
<imgdir name="setitem4">
<imgdir name="0">
<uol name="head" value="../../front/head"/>
</imgdir>
<imgdir name="1">
<uol name="head" value="../../front/head"/>
</imgdir>
<imgdir name="2">
<uol name="head" value="../../front/head"/>
</imgdir>
<imgdir name="3">
<uol name="head" value="../../front/head"/>
</imgdir>
<imgdir name="4">
<uol name="head" value="../../front/head"/>
</imgdir>
<imgdir name="5">
<uol name="head" value="../../front/head"/>
</imgdir>
<imgdir name="6">
<uol name="head" value="../../blink/0/head"/>
</imgdir>
<imgdir name="7">
<uol name="head" value="../../blink/0/head"/>
</imgdir>
<imgdir name="8">
<uol name="head" value="../../front/head"/>
</imgdir>
<imgdir name="9">
<uol name="head" value="../../front/head"/>
</imgdir>
<imgdir name="10">
<uol name="head" value="../../front/head"/>
</imgdir>
<imgdir name="11">
<uol name="head" value="../../front/head"/>
</imgdir>
<imgdir name="12">
<uol name="head" value="../../front/head"/>
</imgdir>
<imgdir name="13">
<uol name="head" value="../../front/head"/>
</imgdir>
<imgdir name="14">
<uol name="head" value="../../front/head"/>
</imgdir>
<imgdir name="15">
<uol name="head" value="../../front/head"/>
</imgdir>
<imgdir name="16">
<uol name="head" value="../../front/head"/>
</imgdir>
<imgdir name="17">
<uol name="head" value="../../front/head"/>
</imgdir>
<imgdir name="18">
<uol name="head" value="../../front/head"/>
</imgdir>
<imgdir name="19">
<uol name="head" value="../../front/head"/>
</imgdir>
<imgdir name="20">
<uol name="head" value="../../front/head"/>
</imgdir>
<imgdir name="21">
<uol name="head" value="../../front/head"/>
</imgdir>
<imgdir name="22">
<uol name="head" value="../../front/head"/>
</imgdir>
<imgdir name="23">
<uol name="head" value="../../front/head"/>
</imgdir>
<imgdir name="24">
<uol name="head" value="../../front/head"/>
</imgdir>
<imgdir name="25">
<uol name="head" value="../../front/head"/>
</imgdir>
<imgdir name="26">
<uol name="head" value="../../front/head"/>
</imgdir>
</imgdir>
</imgdir>
